{
  "schema_version": "2.0",
  "role_id": "WIDAI-LDR-0141",
  "role_name": "Data and AI Research Scientist",
  "ksa_id": "TF-T-007",
  "ksa_text": "Manage application dependencies and package versions for data projects including dependency specification, vulnerability scanning, upgrade planning, and cross-package compatibility verification.",
  "ksa_dimension": "Task",
  "ksa_domain": "TF",
  "pass_1_scoring": {
    "composite_score": 0.4089392113910186,
    "signal_strength": "weak",
    "framework_scores": {
      "dcwf": {
        "composite": 0.3918386587771203,
        "cross_encoder_sts": 0.4335072978303747,
        "bertscore": null,
        "nli_score": null,
        "bi_encoder_cosine": 0.28072228796844184,
        "jaccard": null,
        "top_element_id": "107",
        "top_element_label": "Knowledge of resource management principles and techniques."
      },
      "ddat": {
        "composite": 0.4089392113910186,
        "cross_encoder_sts": 0.45641084337349397,
        "bertscore": null,
        "nli_score": null,
        "bi_encoder_cosine": 0.2823481927710843,
        "jaccard": null,
        "top_element_id": "DDAT-SK-007",
        "top_element_label": "Analysis"
      },
      "eu_ai_act": {
        "composite": 0.37262377622377624,
        "cross_encoder_sts": 0.41143076923076927,
        "bertscore": null,
        "nli_score": null,
        "bi_encoder_cosine": 0.26913846153846155,
        "jaccard": null,
        "top_element_id": "EUAIA-O-006",
        "top_element_label": "Data and data governance"
      },
      "nice": {
        "composite": 0.3916088875980249,
        "cross_encoder_sts": 0.4355840255591054,
        "bertscore": null,
        "nli_score": null,
        "bi_encoder_cosine": 0.27434185303514375,
        "jaccard": null,
        "top_element_id": "K0498",
        "top_element_label": "Knowledge of operational planning processes"
      },
      "nist_ai_rmf": {
        "composite": 0.3725873737373738,
        "cross_encoder_sts": 0.4250055555555556,
        "bertscore": null,
        "nli_score": null,
        "bi_encoder_cosine": 0.23280555555555557,
        "jaccard": null,
        "top_element_id": "AIRMF-MG-2.1",
        "top_element_label": "Strategies to maximize AI benefits and minimize negative impacts are planned, prepared, implemented, documented, and informed by input from relevant AI actors."
      },
      "onet": {
        "composite": 0.38286969696969697,
        "cross_encoder_sts": 0.43220833333333336,
        "bertscore": null,
        "nli_score": null,
        "bi_encoder_cosine": 0.2513,
        "jaccard": null,
        "top_element_id": "2.A.2.d",
        "top_element_label": "Monitoring"
      }
    },
    "top_anchors": [
      {
        "framework": "ddat",
        "element_id": "DDAT-SK-007",
        "element_label": "Analysis",
        "score": 0.4089392113910186
      },
      {
        "framework": "dcwf",
        "element_id": "107",
        "element_label": "Knowledge of resource management principles and techniques.",
        "score": 0.3918386587771203
      },
      {
        "framework": "nice",
        "element_id": "K0498",
        "element_label": "Knowledge of operational planning processes",
        "score": 0.3916088875980249
      },
      {
        "framework": "onet",
        "element_id": "2.A.2.d",
        "element_label": "Monitoring",
        "score": 0.38286969696969697
      },
      {
        "framework": "eu_ai_act",
        "element_id": "EUAIA-O-006",
        "element_label": "Data and data governance",
        "score": 0.37262377622377624
      }
    ],
    "frameworks_with_signal": [
      "dcwf",
      "ddat",
      "eu_ai_act",
      "nice",
      "nist_ai_rmf",
      "onet"
    ],
    "frameworks_no_signal": [],
    "metrics_used": [
      "bi_encoder_cosine",
      "cross_encoder_sts"
    ],
    "metrics_absent": [
      "bertscore",
      "jaccard",
      "nli_score"
    ]
  },
  "pass_2_evaluation": {
    "scope_fit": "in_scope",
    "seniority_fit": "appropriate",
    "preliminary_decision": "include",
    "rationale": "Technical Foundations is a primary or secondary domain for the Data and AI Research Scientist. This task KSA is within scope for the role's expected competency profile and seniority level (senior specialist)."
  },
  "pass_3_adversarial_internal": {
    "outcome": "upheld",
    "challenge": null,
    "rebuttal": null,
    "ruling": "No internal inconsistency identified. Domain scope (Technical Foundations), seniority fit, and signal level are internally consistent with inclusion."
  },
  "pass_4_adversarial_external": {
    "outcome": "upheld",
    "challenge": "Framework signal is weak (composite 0.409). External validation of this task KSA for the Data and AI Research Scientist role relies primarily on domain-level alignment rather than specific framework matches.",
    "evidence": "Technical foundation knowledge is validated by DCWF, NICE framework, and engineering director job postings as required for technical leadership oversight.",
    "ruling": "Upheld: domain-level relevance of Technical Foundations for the Data and AI Research Scientist is corroborated by DAMA-DMBOK, CDO survey data, and role-specific job market analysis, despite weak cross-framework signal."
  },
  "final_decision": "include",
  "decision_confidence": "medium",
  "decision_rationale": "Technical Foundations task KSA is within scope for the Data and AI Research Scientist at the senior specialist tier. Seniority fit is appropriate. All three evaluation passes support inclusion.",
  "adversarial_disagreements": 0,
  "metadata": {
    "evaluated_at": "2026-04-06T18:40:18.852630+00:00",
    "pipeline_version": "1.0"
  }
}