{
  "schema_version": "2.0",
  "role_id": "WIDAI-DSM-0083",
  "role_name": "Domain Data Product Owner",
  "ksa_id": "TF-T-007",
  "ksa_text": "Manage application dependencies and package versions for data projects including dependency specification, vulnerability scanning, upgrade planning, and cross-package compatibility verification.",
  "ksa_dimension": "Task",
  "ksa_domain": "TF",
  "pass_1_scoring": {
    "composite_score": 0.4089392113910186,
    "signal_strength": "weak",
    "framework_scores": {
      "dcwf": {
        "composite": 0.3918386587771203,
        "cross_encoder_sts": 0.4335072978303747,
        "bertscore": null,
        "nli_score": null,
        "bi_encoder_cosine": 0.28072228796844184,
        "jaccard": null,
        "top_element_id": "107",
        "top_element_label": "Knowledge of resource management principles and techniques."
      },
      "ddat": {
        "composite": 0.4089392113910186,
        "cross_encoder_sts": 0.45641084337349397,
        "bertscore": null,
        "nli_score": null,
        "bi_encoder_cosine": 0.2823481927710843,
        "jaccard": null,
        "top_element_id": "DDAT-SK-007",
        "top_element_label": "Analysis"
      },
      "eu_ai_act": {
        "composite": 0.37262377622377624,
        "cross_encoder_sts": 0.41143076923076927,
        "bertscore": null,
        "nli_score": null,
        "bi_encoder_cosine": 0.26913846153846155,
        "jaccard": null,
        "top_element_id": "EUAIA-O-006",
        "top_element_label": "Data and data governance"
      },
      "nice": {
        "composite": 0.3916088875980249,
        "cross_encoder_sts": 0.4355840255591054,
        "bertscore": null,
        "nli_score": null,
        "bi_encoder_cosine": 0.27434185303514375,
        "jaccard": null,
        "top_element_id": "K0498",
        "top_element_label": "Knowledge of operational planning processes"
      },
      "nist_ai_rmf": {
        "composite": 0.3725873737373738,
        "cross_encoder_sts": 0.4250055555555556,
        "bertscore": null,
        "nli_score": null,
        "bi_encoder_cosine": 0.23280555555555557,
        "jaccard": null,
        "top_element_id": "AIRMF-MG-2.1",
        "top_element_label": "Strategies to maximize AI benefits and minimize negative impacts are planned, prepared, implemented, documented, and informed by input from relevant AI actors."
      },
      "onet": {
        "composite": 0.38286969696969697,
        "cross_encoder_sts": 0.43220833333333336,
        "bertscore": null,
        "nli_score": null,
        "bi_encoder_cosine": 0.2513,
        "jaccard": null,
        "top_element_id": "2.A.2.d",
        "top_element_label": "Monitoring"
      }
    },
    "top_anchors": [
      {
        "framework": "ddat",
        "element_id": "DDAT-SK-007",
        "element_label": "Analysis",
        "score": 0.4089392113910186
      },
      {
        "framework": "dcwf",
        "element_id": "107",
        "element_label": "Knowledge of resource management principles and techniques.",
        "score": 0.3918386587771203
      },
      {
        "framework": "nice",
        "element_id": "K0498",
        "element_label": "Knowledge of operational planning processes",
        "score": 0.3916088875980249
      },
      {
        "framework": "onet",
        "element_id": "2.A.2.d",
        "element_label": "Monitoring",
        "score": 0.38286969696969697
      },
      {
        "framework": "eu_ai_act",
        "element_id": "EUAIA-O-006",
        "element_label": "Data and data governance",
        "score": 0.37262377622377624
      }
    ],
    "frameworks_with_signal": [
      "dcwf",
      "ddat",
      "eu_ai_act",
      "nice",
      "nist_ai_rmf",
      "onet"
    ],
    "frameworks_no_signal": [],
    "metrics_used": [
      "bi_encoder_cosine",
      "cross_encoder_sts"
    ],
    "metrics_absent": [
      "bertscore",
      "jaccard",
      "nli_score"
    ]
  },
  "pass_2_evaluation": {
    "scope_fit": "edge_case",
    "seniority_fit": "appropriate",
    "preliminary_decision": "exclude",
    "rationale": "KSA TF-T-007 (Technical Foundations/Task) excluded as edge_case (composite 0.409, highest: DDaT at 0.409). Domain prior: edge. Core hits: 0. OOS hits: 0. Seniority: appropriate. Domain-level data product ownership: data mesh principles, data contracts, domain model governance, inter-domain data agreements, and data product SLA management within a business domain."
  },
  "pass_3_adversarial_internal": {
    "outcome": "upheld",
    "challenge": null,
    "rebuttal": null,
    "ruling": "No inconsistency. Exclude consistent with edge_case classification, composite 0.409, and Technical Foundations (TF) handling."
  },
  "pass_4_adversarial_external": {
    "outcome": "upheld",
    "challenge": "Does market evidence challenge the exclusion of this Technical Foundations KSA (composite 0.409)?",
    "evidence": "Market analysis of Domain Data Product Owner job postings does not surface this Technical Foundations competency as a standard requirement at the relevant level. Exclusion consistent with role focus.",
    "ruling": "Exclusion upheld. Market evidence consistent with exclusion. Final decision: exclude."
  },
  "final_decision": "exclude",
  "decision_confidence": "medium",
  "decision_rationale": "KSA TF-T-007 (Technical Foundations/Task) excluded as edge_case (composite 0.409, highest: DDaT at 0.409). Domain prior: edge. Core hits: 0. OOS hits: 0. Seniority: appropriate. Domain-level data product ownership: data mesh principles, data contracts, domain model governance, inter-domain data agreements, and data product SLA management within a business domain.",
  "adversarial_disagreements": 0,
  "metadata": {
    "evaluated_at": "2026-04-06T18:20:06.208312+00:00",
    "pipeline_version": "1.0"
  }
}