{
  "schema_version": "2.0",
  "role_id": "WIDAI-ANL-0090",
  "role_name": "Quantitative Analyst",
  "ksa_id": "DQ-A-002",
  "ksa_text": "Ability to evaluate data sources for relevance, reliability, completeness, and objectivity to determine how source limitations affect analytical conclusions and data fitness.",
  "ksa_dimension": "Ability",
  "ksa_domain": "DQ",
  "pass_1_scoring": {
    "composite_score": 0.4158589981447124,
    "signal_strength": "weak",
    "framework_scores": {
      "dcwf": {
        "composite": 0.39936307070707067,
        "cross_encoder_sts": 0.4146262222222222,
        "bertscore": null,
        "nli_score": null,
        "bi_encoder_cosine": 0.35866133333333333,
        "jaccard": null,
        "top_element_id": "1079A",
        "top_element_label": "Identify functional- and security-related features to find opportunities for new capability development to exploit or mitigate vulnerabilities."
      },
      "ddat": {
        "composite": 0.4158589981447124,
        "cross_encoder_sts": 0.4427510204081633,
        "bertscore": null,
        "nli_score": null,
        "bi_encoder_cosine": 0.34414693877551017,
        "jaccard": null,
        "top_element_id": "DDAT-SK-023",
        "top_element_label": "Capability building for digital, data and technology"
      },
      "eu_ai_act": {
        "composite": 0.39614917355371904,
        "cross_encoder_sts": 0.41898636363636366,
        "bertscore": null,
        "nli_score": null,
        "bi_encoder_cosine": 0.33525,
        "jaccard": null,
        "top_element_id": "EUAIA-C-003",
        "top_element_label": "Human oversight"
      },
      "nice": {
        "composite": 0.3944067082111437,
        "cross_encoder_sts": 0.4203185483870968,
        "bertscore": null,
        "nli_score": null,
        "bi_encoder_cosine": 0.3253084677419355,
        "jaccard": null,
        "top_element_id": "S0111",
        "top_element_label": "Skill in interfacing with customers"
      },
      "nist_ai_rmf": {
        "composite": 0.3859754820936639,
        "cross_encoder_sts": 0.4140060606060606,
        "bertscore": null,
        "nli_score": null,
        "bi_encoder_cosine": 0.31122727272727274,
        "jaccard": null,
        "top_element_id": "AIRMF-GV-6.2",
        "top_element_label": "Policies and procedures are in place to address AI risks and benefits arising from third-party software and data and other supply chain issues."
      },
      "onet": {
        "composite": 0.4140829545454545,
        "cross_encoder_sts": 0.440575,
        "bertscore": null,
        "nli_score": null,
        "bi_encoder_cosine": 0.3434375,
        "jaccard": null,
        "top_element_id": "2.A.2.a",
        "top_element_label": "Critical Thinking"
      }
    },
    "top_anchors": [
      {
        "framework": "ddat",
        "element_id": "DDAT-SK-023",
        "element_label": "Capability building for digital, data and technology",
        "score": 0.4158589981447124
      },
      {
        "framework": "onet",
        "element_id": "2.A.2.a",
        "element_label": "Critical Thinking",
        "score": 0.4140829545454545
      },
      {
        "framework": "dcwf",
        "element_id": "1079A",
        "element_label": "Identify functional- and security-related features to find opportunities for new capability development to exploit or mitigate vulnerabilities.",
        "score": 0.39936307070707067
      },
      {
        "framework": "eu_ai_act",
        "element_id": "EUAIA-C-003",
        "element_label": "Human oversight",
        "score": 0.39614917355371904
      },
      {
        "framework": "nice",
        "element_id": "S0111",
        "element_label": "Skill in interfacing with customers",
        "score": 0.3944067082111437
      }
    ],
    "frameworks_with_signal": [
      "dcwf",
      "ddat",
      "eu_ai_act",
      "nice",
      "nist_ai_rmf",
      "onet"
    ],
    "frameworks_no_signal": [],
    "metrics_used": [
      "bi_encoder_cosine",
      "cross_encoder_sts"
    ],
    "metrics_absent": [
      "bertscore",
      "jaccard",
      "nli_score"
    ]
  },
  "pass_2_evaluation": {
    "scope_fit": "moderate_fit",
    "seniority_fit": "appropriate",
    "preliminary_decision": "exclude",
    "rationale": "KSA DQ-A-002 (DQ, Ability) does not clear the moderate fit inclusion threshold of 0.43. Composite score 0.4159 is insufficient to establish relevance to quantitative analysis, statistical modeling, and financial analytics at IC-to-senior-IC level. Framework signals (ddat=0.416, onet=0.414, dcwf=0.399) do not demonstrate sufficient alignment with core analytics/BI work."
  },
  "pass_3_adversarial_internal": {
    "outcome": "overturned",
    "challenge": "DQ domain KSA DQ-A-002 excluded at composite 0.4159, but KSA text contains direct analytics-domain signals. Internal consistency: the presence of analytics terminology in a moderate fit KSA at score 0.4159 suggests the threshold is excluding genuinely relevant content.",
    "rebuttal": "Composite 0.4159 with confirmed analytics-domain terminology for a DQ (moderate fit) KSA indicates real role relevance for Quantitative Analyst. The 0.43 threshold is a calibration heuristic; text-signal confirmation overrides marginal score shortfall at this level.",
    "ruling": "P2 exclude overturned. DQ KSA with composite 0.4159 and confirmed analytics-domain text signals included on internal consistency grounds."
  },
  "pass_4_adversarial_external": {
    "outcome": "upheld",
    "challenge": "External validation: does KSA DQ-A-002 (DQ, composite 0.4159) appear in published data analyst / BI role profiles and workforce frameworks?",
    "evidence": "KSA content aligns with DCAT-AP, DAMA DMBOK data quality competency framework; DQ awareness is a documented expectation in senior IC analyst roles. Analytics-domain terminology in KSA text confirms practical relevance to IC ANL work. Composite 0.4159 with signal across ddat=0.416, onet=0.414, dcwf=0.399 is consistent with documented ANL competency expectations at IC-to-senior-IC level. External ground truth supports inclusion.",
    "ruling": "P3 include upheld. External evidence from DQ-domain frameworks confirms KSA relevance to Quantitative Analyst at IC-to-senior-IC level."
  },
  "final_decision": "include",
  "decision_confidence": "medium",
  "decision_rationale": "Single adversarial overturn by P3 internal consistency. Final decision: include. Composite 0.4159, domain DQ. Medium confidence \u2014 one agent challenged and overturned the preliminary assessment.",
  "adversarial_disagreements": 1,
  "metadata": {
    "evaluated_at": "2026-04-06T18:15:33.248726+00:00",
    "pipeline_version": "1.0"
  }
}