{
  "framework_id": "NIST_NICE",
  "framework_name": "Workforce Framework for Cybersecurity (NICE Framework)",
  "version": "Components v2.1.0",
  "publication_date": "2025-12-03",
  "governing_document": "NIST SP 800-181 Rev. 1 (November 2020)",
  "governing_document_doi": "https://doi.org/10.6028/NIST.SP.800-181r1",
  "components_source": "https://csrc.nist.gov/projects/cprt/catalog#/cprt/framework/version/SP_800_181_2_1_0/home",
  "json_source": "https://csrc.nist.gov/csrc/media/Projects/cprt/documents/nice/cprt_SP_800_181_2_1_0_12-11-2025.json",
  "xlsx_source": "https://www.nist.gov/system/files/documents/2025/12/31/NICE%20Framework%20Components%20v2.1.0.xlsx",
  "publisher": "National Institute of Standards and Technology (NIST)",
  "license": "PUBLIC (U.S. Government work, not subject to copyright)",
  "commercial_status": "GREEN",
  "access_date": "2026-04-01",
  "local_files": [
    "sources/nice_framework/NICE_Framework_Components_v2.1.0.xlsx",
    "sources/nice_framework/cprt_SP_800_181_2_1_0.json"
  ],
  "element_counts": {
    "tasks": 946,
    "knowledge": 662,
    "skills": 540,
    "work_roles": 41,
    "categories": 5,
    "competency_areas": 11
  }
}